Metadata-Version: 2.1
Name: minpipe
Version: 0.1.0
Summary: A minimal library for building one-off concurrent data pipelines
Home-page: https://github.com/clane9/minpipe
Author: Connor Lane
License: MIT
Platform: UNKNOWN
Requires-Python: >=3.7
